[{"lodestone_id":8901832,"server":"Shinryu","rank_server":1,"rank_server_previous":1,"points":12380},{"lodestone_id":3202750,"server":"Shinryu","rank_server":2,"rank_server_previous":2,"points":12100},{"lodestone_id":7910109,"server":"Shinryu","rank_server":3,"rank_server_previous":3,"points":11930},{"lodestone_id":7114972,"server":"Shinryu","rank_server":4,"rank_server_previous":4,"points":11525},{"lodestone_id":5369500,"server":"Shinryu","rank_server":5,"rank_server_previous":5,"points":11485},{"lodestone_id":6772797,"server":"Shinryu","rank_server":6,"rank_server_previous":6,"points":11395},{"lodestone_id":1154543,"server":"Shinryu","rank_server":7,"rank_server_previous":7,"points":11280},{"lodestone_id":9158933,"server":"Shinryu","rank_server":8,"rank_server_previous":8,"points":10895},{"lodestone_id":8017537,"server":"Shinryu","rank_server":9,"rank_server_previous":9,"points":10765},{"lodestone_id":12546020,"server":"Shinryu","rank_server":10,"rank_server_previous":10,"points":10600},{"lodestone_id":7081816,"server":"Shinryu","rank_server":11,"rank_server_previous":11,"points":10460},{"lodestone_id":8267884,"server":"Shinryu","rank_server":12,"rank_server_previous":12,"points":10335},{"lodestone_id":9329118,"server":"Shinryu","rank_server":13,"rank_server_previous":13,"points":10260},{"lodestone_id":8342674,"server":"Shinryu","rank_server":14,"rank_server_previous":14,"points":10235},{"lodestone_id":4668938,"server":"Shinryu","rank_server":15,"rank_server_previous":15,"points":10070},{"lodestone_id":7170083,"server":"Shinryu","rank_server":16,"rank_server_previous":16,"points":10060},{"lodestone_id":9223685,"server":"Shinryu","rank_server":17,"rank_server_previous":17,"points":10030},{"lodestone_id":285201,"server":"Shinryu","rank_server":18,"rank_server_previous":18,"points":9945},{"lodestone_id":4467333,"server":"Shinryu","rank_server":19,"rank_server_previous":19,"points":9940},{"lodestone_id":7409309,"server":"Shinryu","rank_server":20,"rank_server_previous":20,"points":9850},{"lodestone_id":8919682,"server":"Shinryu","rank_server":21,"rank_server_previous":21,"points":9820},{"lodestone_id":5532802,"server":"Shinryu","rank_server":22,"rank_server_previous":22,"points":9810},{"lodestone_id":6207716,"server":"Shinryu","rank_server":23,"rank_server_previous":23,"points":9670},{"lodestone_id":7535590,"server":"Shinryu","rank_server":24,"rank_server_previous":24,"points":9655},{"lodestone_id":7629934,"server":"Shinryu","rank_server":25,"rank_server_previous":25,"points":9640},{"lodestone_id":8534144,"server":"Shinryu","rank_server":26,"rank_server_previous":26,"points":9605},{"lodestone_id":3652671,"server":"Shinryu","rank_server":27,"rank_server_previous":27,"points":9605},{"lodestone_id":4436131,"server":"Shinryu","rank_server":28,"rank_server_previous":28,"points":9595},{"lodestone_id":7038544,"server":"Shinryu","rank_server":29,"rank_server_previous":29,"points":9585},{"lodestone_id":3152165,"server":"Shinryu","rank_server":30,"rank_server_previous":30,"points":9585},{"lodestone_id":11429786,"server":"Shinryu","rank_server":31,"rank_server_previous":31,"points":9560},{"lodestone_id":8624290,"server":"Shinryu","rank_server":32,"rank_server_previous":32,"points":9515},{"lodestone_id":7198294,"server":"Shinryu","rank_server":33,"rank_server_previous":33,"points":9505},{"lodestone_id":3919646,"server":"Shinryu","rank_server":34,"rank_server_previous":34,"points":9480},{"lodestone_id":8474890,"server":"Shinryu","rank_server":35,"rank_server_previous":35,"points":9430},{"lodestone_id":12324822,"server":"Shinryu","rank_server":36,"rank_server_previous":36,"points":9415},{"lodestone_id":7194794,"server":"Shinryu","rank_server":37,"rank_server_previous":37,"points":9370},{"lodestone_id":7622727,"server":"Shinryu","rank_server":38,"rank_server_previous":38,"points":9355},{"lodestone_id":13858079,"server":"Shinryu","rank_server":39,"rank_server_previous":39,"points":9345},{"lodestone_id":3240372,"server":"Shinryu","rank_server":40,"rank_server_previous":40,"points":9340},{"lodestone_id":5618164,"server":"Shinryu","rank_server":41,"rank_server_previous":41,"points":9295},{"lodestone_id":7900774,"server":"Shinryu","rank_server":42,"rank_server_previous":42,"points":9280},{"lodestone_id":7034784,"server":"Shinryu","rank_server":43,"rank_server_previous":43,"points":9275},{"lodestone_id":1585692,"server":"Shinryu","rank_server":44,"rank_server_previous":44,"points":9265},{"lodestone_id":10768936,"server":"Shinryu","rank_server":45,"rank_server_previous":45,"points":9250},{"lodestone_id":7191279,"server":"Shinryu","rank_server":46,"rank_server_previous":46,"points":9245},{"lodestone_id":3170392,"server":"Shinryu","rank_server":47,"rank_server_previous":47,"points":9245},{"lodestone_id":2633523,"server":"Shinryu","rank_server":48,"rank_server_previous":48,"points":9215},{"lodestone_id":11901757,"server":"Shinryu","rank_server":49,"rank_server_previous":49,"points":9200},{"lodestone_id":7158810,"server":"Shinryu","rank_server":50,"rank_server_previous":50,"points":9195},{"lodestone_id":3967308,"server":"Shinryu","rank_server":51,"rank_server_previous":51,"points":9185},{"lodestone_id":9381792,"server":"Shinryu","rank_server":52,"rank_server_previous":52,"points":9180},{"lodestone_id":8443848,"server":"Shinryu","rank_server":53,"rank_server_previous":53,"points":9140},{"lodestone_id":7277672,"server":"Shinryu","rank_server":54,"rank_server_previous":54,"points":9140},{"lodestone_id":1976932,"server":"Shinryu","rank_server":55,"rank_server_previous":55,"points":9125},{"lodestone_id":12723722,"server":"Shinryu","rank_server":56,"rank_server_previous":56,"points":9120},{"lodestone_id":7038485,"server":"Shinryu","rank_server":57,"rank_server_previous":57,"points":9115},{"lodestone_id":1227219,"server":"Shinryu","rank_server":58,"rank_server_previous":58,"points":9075},{"lodestone_id":8246285,"server":"Shinryu","rank_server":59,"rank_server_previous":59,"points":9060},{"lodestone_id":11129393,"server":"Shinryu","rank_server":60,"rank_server_previous":60,"points":9050},{"lodestone_id":7526308,"server":"Shinryu","rank_server":61,"rank_server_previous":61,"points":9015},{"lodestone_id":7747113,"server":"Shinryu","rank_server":62,"rank_server_previous":62,"points":9010},{"lodestone_id":9923627,"server":"Shinryu","rank_server":63,"rank_server_previous":63,"points":9005},{"lodestone_id":10420416,"server":"Shinryu","rank_server":64,"rank_server_previous":64,"points":9000},{"lodestone_id":11363958,"server":"Shinryu","rank_server":65,"rank_server_previous":65,"points":8975},{"lodestone_id":8840572,"server":"Shinryu","rank_server":66,"rank_server_previous":66,"points":8950},{"lodestone_id":10660191,"server":"Shinryu","rank_server":67,"rank_server_previous":67,"points":8930},{"lodestone_id":8642969,"server":"Shinryu","rank_server":68,"rank_server_previous":68,"points":8890},{"lodestone_id":8337565,"server":"Shinryu","rank_server":69,"rank_server_previous":69,"points":8865},{"lodestone_id":8845807,"server":"Shinryu","rank_server":70,"rank_server_previous":70,"points":8840},{"lodestone_id":7621596,"server":"Shinryu","rank_server":71,"rank_server_previous":71,"points":8840},{"lodestone_id":7038598,"server":"Shinryu","rank_server":72,"rank_server_previous":72,"points":8825},{"lodestone_id":11723575,"server":"Shinryu","rank_server":73,"rank_server_previous":73,"points":8815},{"lodestone_id":4999339,"server":"Shinryu","rank_server":74,"rank_server_previous":74,"points":8810},{"lodestone_id":14112170,"server":"Shinryu","rank_server":75,"rank_server_previous":75,"points":8795},{"lodestone_id":11406945,"server":"Shinryu","rank_server":76,"rank_server_previous":76,"points":8795},{"lodestone_id":8570357,"server":"Shinryu","rank_server":77,"rank_server_previous":77,"points":8790},{"lodestone_id":8606926,"server":"Shinryu","rank_server":78,"rank_server_previous":78,"points":8785},{"lodestone_id":7043698,"server":"Shinryu","rank_server":79,"rank_server_previous":79,"points":8775},{"lodestone_id":10341804,"server":"Shinryu","rank_server":80,"rank_server_previous":80,"points":8765},{"lodestone_id":5951124,"server":"Shinryu","rank_server":81,"rank_server_previous":81,"points":8750},{"lodestone_id":6602028,"server":"Shinryu","rank_server":82,"rank_server_previous":82,"points":8715},{"lodestone_id":4337735,"server":"Shinryu","rank_server":83,"rank_server_previous":83,"points":8715},{"lodestone_id":7024137,"server":"Shinryu","rank_server":84,"rank_server_previous":84,"points":8710},{"lodestone_id":3491124,"server":"Shinryu","rank_server":85,"rank_server_previous":85,"points":8710},{"lodestone_id":10311264,"server":"Shinryu","rank_server":86,"rank_server_previous":86,"points":8705},{"lodestone_id":3275623,"server":"Shinryu","rank_server":87,"rank_server_previous":87,"points":8700},{"lodestone_id":7181665,"server":"Shinryu","rank_server":88,"rank_server_previous":88,"points":8680},{"lodestone_id":7035142,"server":"Shinryu","rank_server":89,"rank_server_previous":89,"points":8630},{"lodestone_id":3330792,"server":"Shinryu","rank_server":90,"rank_server_previous":90,"points":8630},{"lodestone_id":3152139,"server":"Shinryu","rank_server":91,"rank_server_previous":91,"points":8620},{"lodestone_id":7927724,"server":"Shinryu","rank_server":92,"rank_server_previous":92,"points":8615},{"lodestone_id":2225631,"server":"Shinryu","rank_server":93,"rank_server_previous":93,"points":8610},{"lodestone_id":7115325,"server":"Shinryu","rank_server":94,"rank_server_previous":94,"points":8600},{"lodestone_id":10962566,"server":"Shinryu","rank_server":95,"rank_server_previous":95,"points":8595},{"lodestone_id":7518726,"server":"Shinryu","rank_server":96,"rank_server_previous":96,"points":8590},{"lodestone_id":1244265,"server":"Shinryu","rank_server":97,"rank_server_previous":97,"points":8585},{"lodestone_id":3221894,"server":"Shinryu","rank_server":98,"rank_server_previous":98,"points":8580},{"lodestone_id":8945811,"server":"Shinryu","rank_server":99,"rank_server_previous":99,"points":8575},{"lodestone_id":5994907,"server":"Shinryu","rank_server":100,"rank_server_previous":100,"points":8570}]